AA_stat/AA_stat.py
AA_stat/__init__.py
AA_stat/aa_search.py
AA_stat/default.cfg
AA_stat/html.py
AA_stat/io.py
AA_stat/localization.py
AA_stat/main.py
AA_stat/open_search.params
AA_stat/recommendations.py
AA_stat/report.template
AA_stat/stats.py
AA_stat/tests.py
AA_stat/unimod.xml
AA_stat/utils.py
AA_stat/version.py
AA_stat/gui/__init__.py
AA_stat/gui/gui.py
AA_stat/gui/logging.py
AA_stat/gui/shortcut.py
AA_stat-2.6.1.dist-info/LICENSE
AA_stat-2.6.1.dist-info/METADATA
AA_stat-2.6.1.dist-info/WHEEL
AA_stat-2.6.1.dist-info/entry_points.txt
AA_stat-2.6.1.dist-info/top_level.txt
AA_stat-2.6.1.dist-info/RECORD
