Metadata-Version: 2.1
Name: AA_stat
Version: 2.6.1
Summary: A utility for validation of peptide identification results in proteomics using amino acid counting.
Author: Julia Bubis & Lev Levitsky
Author-email: julia.bubis@gmail.com
License: License :: OSI Approved :: Apache Software License
Classifier: Intended Audience :: Science/Research
Classifier: Programming Language :: Python :: 3
Classifier: Topic :: Scientific/Engineering :: Bio-Informatics
Classifier: Topic :: Scientific/Engineering :: Chemistry
Classifier: Topic :: Scientific/Engineering :: Physics
Requires-Python: >=3.8
License-File: LICENSE
Requires-Dist: pyteomics>4.7.2
Requires-Dist: pandas>=1.4
Requires-Dist: seaborn
Requires-Dist: scipy
Requires-Dist: numpy
Requires-Dist: lxml
Requires-Dist: jinja2>=3.1.2
Requires-Dist: scikit-learn
